{
    "Name": "Marine Costs - Financial Itemized",
    "Width": 923.0,
    "Height": 208.0,
    "FormObjects": {
        "Label": {
            "Visible": 1.0,
            "ObjectProperties": {
                "Name": {
                    "Type": 5.0,
                    "String": "capex_check"
                },
                "X": {
                    "Type": 3.0,
                    "Integer": 147.0
                },
                "Y": {
                    "Type": 3.0,
                    "Integer": 252.0
                },
                "Width": {
                    "Type": 3.0,
                    "Integer": 90.0
                },
                "Height": {
                    "Type": 3.0,
                    "Integer": 24.0
                },
                "Tool Tip": {
                    "Type": 5.0,
                    "String": ""
                },
                "Caption": {
                    "Type": 5.0,
                    "String": ""
                },
                "TextColour": {
                    "Type": 4.0,
                    "Color": {
                        "Red": 0.0,
                        "Green": 0.0,
                        "Blue": 0.0,
                        "Alpha": 255.0
                    }
                },
                "Bold": {
                    "Type": 2.0,
                    "Boolean": 0.0
                },
                "FontSize": {
                    "Type": 3.0,
                    "Integer": 0.0
                },
                "WordWrap": {
                    "Type": 2.0,
                    "Boolean": 0.0
                },
                "AlignRight": {
                    "Type": 2.0,
                    "Boolean": 0.0
                },
                "AlignTop": {
                    "Type": 2.0,
                    "Boolean": 0.0
                }
            }
        },
        "Numeric": {
            "Visible": 1.0,
            "ObjectProperties": {
                "Name": {
                    "Type": 5.0,
                    "String": "debt_service_reserve_account_cost"
                },
                "X": {
                    "Type": 3.0,
                    "Integer": 339.0
                },
                "Y": {
                    "Type": 3.0,
                    "Integer": 102.0
                },
                "Width": {
                    "Type": 3.0,
                    "Integer": 90.0
                },
                "Height": {
                    "Type": 3.0,
                    "Integer": 24.0
                },
                "Tool Tip": {
                    "Type": 5.0,
                    "String": ""
                },
                "Value": {
                    "Type": 1.0,
                    "Double": 0.0
                },
                "Mode": {
                    "Type": 3.0,
                    "Integer": 1.0
                },
                "Format": {
                    "Type": 3.0,
                    "Integer": 0.0
                },
                "Decimals": {
                    "Type": 3.0,
                    "Integer": 0.0
                },
                "Prefix": {
                    "Type": 5.0,
                    "String": "$"
                },
                "Suffix": {
                    "Type": 5.0,
                    "String": ""
                },
                "ThousandsSep": {
                    "Type": 2.0,
                    "Boolean": 1.0
                },
                "Editable": {
                    "Type": 2.0,
                    "Boolean": 1.0
                },
                "ForeColour": {
                    "Type": 4.0,
                    "Color": {
                        "Red": 0.0,
                        "Green": 0.0,
                        "Blue": 0.0,
                        "Alpha": 255.0
                    }
                },
                "BackColour": {
                    "Type": 4.0,
                    "Color": {
                        "Red": 255.0,
                        "Green": 255.0,
                        "Blue": 255.0,
                        "Alpha": 255.0
                    }
                },
                "TabOrder": {
                    "Type": 3.0,
                    "Integer": -1.0
                }
            }
        },
        "Numeric": {
            "Visible": 1.0,
            "ObjectProperties": {
                "Name": {
                    "Type": 5.0,
                    "String": "decommissioning_reserve_account_cost"
                },
                "X": {
                    "Type": 3.0,
                    "Integer": 339.0
                },
                "Y": {
                    "Type": 3.0,
                    "Integer": 132.0
                },
                "Width": {
                    "Type": 3.0,
                    "Integer": 90.0
                },
                "Height": {
                    "Type": 3.0,
                    "Integer": 24.0
                },
                "Tool Tip": {
                    "Type": 5.0,
                    "String": ""
                },
                "Value": {
                    "Type": 1.0,
                    "Double": 0.0
                },
                "Mode": {
                    "Type": 3.0,
                    "Integer": 1.0
                },
                "Format": {
                    "Type": 3.0,
                    "Integer": 0.0
                },
                "Decimals": {
                    "Type": 3.0,
                    "Integer": 0.0
                },
                "Prefix": {
                    "Type": 5.0,
                    "String": "$"
                },
                "Suffix": {
                    "Type": 5.0,
                    "String": ""
                },
                "ThousandsSep": {
                    "Type": 2.0,
                    "Boolean": 1.0
                },
                "Editable": {
                    "Type": 2.0,
                    "Boolean": 1.0
                },
                "ForeColour": {
                    "Type": 4.0,
                    "Color": {
                        "Red": 0.0,
                        "Green": 0.0,
                        "Blue": 0.0,
                        "Alpha": 255.0
                    }
                },
                "BackColour": {
                    "Type": 4.0,
                    "Color": {
                        "Red": 255.0,
                        "Green": 255.0,
                        "Blue": 255.0,
                        "Alpha": 255.0
                    }
                },
                "TabOrder": {
                    "Type": 3.0,
                    "Integer": -1.0
                }
            }
        },
        "Label": {
            "Visible": 1.0,
            "ObjectProperties": {
                "Name": {
                    "Type": 5.0,
                    "String": "financial_override_check"
                },
                "X": {
                    "Type": 3.0,
                    "Integer": 33.0
                },
                "Y": {
                    "Type": 3.0,
                    "Integer": 249.0
                },
                "Width": {
                    "Type": 3.0,
                    "Integer": 90.0
                },
                "Height": {
                    "Type": 3.0,
                    "Integer": 24.0
                },
                "Tool Tip": {
                    "Type": 5.0,
                    "String": ""
                },
                "Caption": {
                    "Type": 5.0,
                    "String": ""
                },
                "TextColour": {
                    "Type": 4.0,
                    "Color": {
                        "Red": 0.0,
                        "Green": 0.0,
                        "Blue": 0.0,
                        "Alpha": 255.0
                    }
                },
                "Bold": {
                    "Type": 2.0,
                    "Boolean": 0.0
                },
                "FontSize": {
                    "Type": 3.0,
                    "Integer": 0.0
                },
                "WordWrap": {
                    "Type": 2.0,
                    "Boolean": 0.0
                },
                "AlignRight": {
                    "Type": 2.0,
                    "Boolean": 0.0
                },
                "AlignTop": {
                    "Type": 2.0,
                    "Boolean": 0.0
                }
            }
        },
        "Label": {
            "Visible": 1.0,
            "ObjectProperties": {
                "Name": {
                    "Type": 5.0,
                    "String": "financial_override_label"
                },
                "X": {
                    "Type": 3.0,
                    "Integer": 537.0
                },
                "Y": {
                    "Type": 3.0,
                    "Integer": 63.0
                },
                "Width": {
                    "Type": 3.0,
                    "Integer": 246.0
                },
                "Height": {
                    "Type": 3.0,
                    "Integer": 114.0
                },
                "Tool Tip": {
                    "Type": 5.0,
                    "String": ""
                },
                "Caption": {
                    "Type": 5.0,
                    "String": "The category cost breakdown cannot be used when 'Override cost structure' is selected. The values in the category cost columns will not be applied."
                },
                "TextColour": {
                    "Type": 4.0,
                    "Color": {
                        "Red": 255.0,
                        "Green": 0.0,
                        "Blue": 0.0,
                        "Alpha": 255.0
                    }
                },
                "Bold": {
                    "Type": 2.0,
                    "Boolean": 0.0
                },
                "FontSize": {
                    "Type": 3.0,
                    "Integer": 0.0
                },
                "WordWrap": {
                    "Type": 2.0,
                    "Boolean": 1.0
                },
                "AlignRight": {
                    "Type": 2.0,
                    "Boolean": 0.0
                },
                "AlignTop": {
                    "Type": 2.0,
                    "Boolean": 1.0
                }
            }
        },
        "Label": {
            "Visible": 1.0,
            "ObjectProperties": {
                "Name": {
                    "Type": 5.0,
                    "String": "itemized_check_reserve_accounts"
                },
                "X": {
                    "Type": 3.0,
                    "Integer": 282.0
                },
                "Y": {
                    "Type": 3.0,
                    "Integer": 255.0
                },
                "Width": {
                    "Type": 3.0,
                    "Integer": 90.0
                },
                "Height": {
                    "Type": 3.0,
                    "Integer": 24.0
                },
                "Tool Tip": {
                    "Type": 5.0,
                    "String": ""
                },
                "Caption": {
                    "Type": 5.0,
                    "String": ""
                },
                "TextColour": {
                    "Type": 4.0,
                    "Color": {
                        "Red": 0.0,
                        "Green": 0.0,
                        "Blue": 0.0,
                        "Alpha": 255.0
                    }
                },
                "Bold": {
                    "Type": 2.0,
                    "Boolean": 0.0
                },
                "FontSize": {
                    "Type": 3.0,
                    "Integer": 0.0
                },
                "WordWrap": {
                    "Type": 2.0,
                    "Boolean": 0.0
                },
                "AlignRight": {
                    "Type": 2.0,
                    "Boolean": 0.0
                },
                "AlignTop": {
                    "Type": 2.0,
                    "Boolean": 0.0
                }
            }
        },
        "Numeric": {
            "Visible": 1.0,
            "ObjectProperties": {
                "Name": {
                    "Type": 5.0,
                    "String": "maintenance_reserve_account_cost"
                },
                "X": {
                    "Type": 3.0,
                    "Integer": 339.0
                },
                "Y": {
                    "Type": 3.0,
                    "Integer": 72.0
                },
                "Width": {
                    "Type": 3.0,
                    "Integer": 90.0
                },
                "Height": {
                    "Type": 3.0,
                    "Integer": 24.0
                },
                "Tool Tip": {
                    "Type": 5.0,
                    "String": ""
                },
                "Value": {
                    "Type": 1.0,
                    "Double": 0.0
                },
                "Mode": {
                    "Type": 3.0,
                    "Integer": 1.0
                },
                "Format": {
                    "Type": 3.0,
                    "Integer": 0.0
                },
                "Decimals": {
                    "Type": 3.0,
                    "Integer": 0.0
                },
                "Prefix": {
                    "Type": 5.0,
                    "String": "$"
                },
                "Suffix": {
                    "Type": 5.0,
                    "String": ""
                },
                "ThousandsSep": {
                    "Type": 2.0,
                    "Boolean": 1.0
                },
                "Editable": {
                    "Type": 2.0,
                    "Boolean": 1.0
                },
                "ForeColour": {
                    "Type": 4.0,
                    "Color": {
                        "Red": 0.0,
                        "Green": 0.0,
                        "Blue": 0.0,
                        "Alpha": 255.0
                    }
                },
                "BackColour": {
                    "Type": 4.0,
                    "Color": {
                        "Red": 255.0,
                        "Green": 255.0,
                        "Blue": 255.0,
                        "Alpha": 255.0
                    }
                },
                "TabOrder": {
                    "Type": 3.0,
                    "Integer": -1.0
                }
            }
        },
        "GroupBox": {
            "Visible": 1.0,
            "ObjectProperties": {
                "Name": {
                    "Type": 5.0,
                    "String": "object 4"
                },
                "X": {
                    "Type": 3.0,
                    "Integer": 9.0
                },
                "Y": {
                    "Type": 3.0,
                    "Integer": 15.0
                },
                "Width": {
                    "Type": 3.0,
                    "Integer": 900.0
                },
                "Height": {
                    "Type": 3.0,
                    "Integer": 186.0
                },
                "Tool Tip": {
                    "Type": 5.0,
                    "String": ""
                },
                "Caption": {
                    "Type": 5.0,
                    "String": "Reserve Accounts"
                },
                "Bold": {
                    "Type": 2.0,
                    "Boolean": 1.0
                }
            }
        },
        "Label": {
            "Visible": 1.0,
            "ObjectProperties": {
                "Name": {
                    "Type": 5.0,
                    "String": "object 7"
                },
                "X": {
                    "Type": 3.0,
                    "Integer": 207.0
                },
                "Y": {
                    "Type": 3.0,
                    "Integer": 39.0
                },
                "Width": {
                    "Type": 3.0,
                    "Integer": 222.0
                },
                "Height": {
                    "Type": 3.0,
                    "Integer": 24.0
                },
                "Tool Tip": {
                    "Type": 5.0,
                    "String": ""
                },
                "Caption": {
                    "Type": 5.0,
                    "String": "Category totals"
                },
                "TextColour": {
                    "Type": 4.0,
                    "Color": {
                        "Red": 0.0,
                        "Green": 0.0,
                        "Blue": 0.0,
                        "Alpha": 255.0
                    }
                },
                "Bold": {
                    "Type": 2.0,
                    "Boolean": 0.0
                },
                "FontSize": {
                    "Type": 3.0,
                    "Integer": 0.0
                },
                "WordWrap": {
                    "Type": 2.0,
                    "Boolean": 0.0
                },
                "AlignRight": {
                    "Type": 2.0,
                    "Boolean": 1.0
                },
                "AlignTop": {
                    "Type": 2.0,
                    "Boolean": 0.0
                }
            }
        },
        "Label": {
            "Visible": 1.0,
            "ObjectProperties": {
                "Name": {
                    "Type": 5.0,
                    "String": "object 72751"
                },
                "X": {
                    "Type": 3.0,
                    "Integer": 21.0
                },
                "Y": {
                    "Type": 3.0,
                    "Integer": 132.0
                },
                "Width": {
                    "Type": 3.0,
                    "Integer": 318.0
                },
                "Height": {
                    "Type": 3.0,
                    "Integer": 24.0
                },
                "Tool Tip": {
                    "Type": 5.0,
                    "String": ""
                },
                "Caption": {
                    "Type": 5.0,
                    "String": "Decommissioning reserve account"
                },
                "TextColour": {
                    "Type": 4.0,
                    "Color": {
                        "Red": 0.0,
                        "Green": 0.0,
                        "Blue": 0.0,
                        "Alpha": 255.0
                    }
                },
                "Bold": {
                    "Type": 2.0,
                    "Boolean": 1.0
                },
                "FontSize": {
                    "Type": 3.0,
                    "Integer": 0.0
                },
                "WordWrap": {
                    "Type": 2.0,
                    "Boolean": 0.0
                },
                "AlignRight": {
                    "Type": 2.0,
                    "Boolean": 1.0
                },
                "AlignTop": {
                    "Type": 2.0,
                    "Boolean": 0.0
                }
            }
        },
        "Label": {
            "Visible": 1.0,
            "ObjectProperties": {
                "Name": {
                    "Type": 5.0,
                    "String": "object 728"
                },
                "X": {
                    "Type": 3.0,
                    "Integer": 21.0
                },
                "Y": {
                    "Type": 3.0,
                    "Integer": 102.0
                },
                "Width": {
                    "Type": 3.0,
                    "Integer": 318.0
                },
                "Height": {
                    "Type": 3.0,
                    "Integer": 24.0
                },
                "Tool Tip": {
                    "Type": 5.0,
                    "String": ""
                },
                "Caption": {
                    "Type": 5.0,
                    "String": "Debt service reserve account"
                },
                "TextColour": {
                    "Type": 4.0,
                    "Color": {
                        "Red": 0.0,
                        "Green": 0.0,
                        "Blue": 0.0,
                        "Alpha": 255.0
                    }
                },
                "Bold": {
                    "Type": 2.0,
                    "Boolean": 1.0
                },
                "FontSize": {
                    "Type": 3.0,
                    "Integer": 0.0
                },
                "WordWrap": {
                    "Type": 2.0,
                    "Boolean": 0.0
                },
                "AlignRight": {
                    "Type": 2.0,
                    "Boolean": 1.0
                },
                "AlignTop": {
                    "Type": 2.0,
                    "Boolean": 0.0
                }
            }
        },
        "Label": {
            "Visible": 1.0,
            "ObjectProperties": {
                "Name": {
                    "Type": 5.0,
                    "String": "object 72937"
                },
                "X": {
                    "Type": 3.0,
                    "Integer": 18.0
                },
                "Y": {
                    "Type": 3.0,
                    "Integer": 72.0
                },
                "Width": {
                    "Type": 3.0,
                    "Integer": 321.0
                },
                "Height": {
                    "Type": 3.0,
                    "Integer": 24.0
                },
                "Tool Tip": {
                    "Type": 5.0,
                    "String": ""
                },
                "Caption": {
                    "Type": 5.0,
                    "String": "Maintenance reserve account"
                },
                "TextColour": {
                    "Type": 4.0,
                    "Color": {
                        "Red": 0.0,
                        "Green": 0.0,
                        "Blue": 0.0,
                        "Alpha": 255.0
                    }
                },
                "Bold": {
                    "Type": 2.0,
                    "Boolean": 1.0
                },
                "FontSize": {
                    "Type": 3.0,
                    "Integer": 0.0
                },
                "WordWrap": {
                    "Type": 2.0,
                    "Boolean": 0.0
                },
                "AlignRight": {
                    "Type": 2.0,
                    "Boolean": 1.0
                },
                "AlignTop": {
                    "Type": 2.0,
                    "Boolean": 0.0
                }
            }
        },
        "Label": {
            "Visible": 1.0,
            "ObjectProperties": {
                "Name": {
                    "Type": 5.0,
                    "String": "object 731"
                },
                "X": {
                    "Type": 3.0,
                    "Integer": 24.0
                },
                "Y": {
                    "Type": 3.0,
                    "Integer": 162.0
                },
                "Width": {
                    "Type": 3.0,
                    "Integer": 315.0
                },
                "Height": {
                    "Type": 3.0,
                    "Integer": 24.0
                },
                "Tool Tip": {
                    "Type": 5.0,
                    "String": ""
                },
                "Caption": {
                    "Type": 5.0,
                    "String": "Other reserve accounts"
                },
                "TextColour": {
                    "Type": 4.0,
                    "Color": {
                        "Red": 0.0,
                        "Green": 0.0,
                        "Blue": 0.0,
                        "Alpha": 255.0
                    }
                },
                "Bold": {
                    "Type": 2.0,
                    "Boolean": 1.0
                },
                "FontSize": {
                    "Type": 3.0,
                    "Integer": 0.0
                },
                "WordWrap": {
                    "Type": 2.0,
                    "Boolean": 0.0
                },
                "AlignRight": {
                    "Type": 2.0,
                    "Boolean": 1.0
                },
                "AlignTop": {
                    "Type": 2.0,
                    "Boolean": 0.0
                }
            }
        },
        "Numeric": {
            "Visible": 1.0,
            "ObjectProperties": {
                "Name": {
                    "Type": 5.0,
                    "String": "other_reserve_account_cost"
                },
                "X": {
                    "Type": 3.0,
                    "Integer": 339.0
                },
                "Y": {
                    "Type": 3.0,
                    "Integer": 162.0
                },
                "Width": {
                    "Type": 3.0,
                    "Integer": 90.0
                },
                "Height": {
                    "Type": 3.0,
                    "Integer": 24.0
                },
                "Tool Tip": {
                    "Type": 5.0,
                    "String": ""
                },
                "Value": {
                    "Type": 1.0,
                    "Double": 0.0
                },
                "Mode": {
                    "Type": 3.0,
                    "Integer": 1.0
                },
                "Format": {
                    "Type": 3.0,
                    "Integer": 0.0
                },
                "Decimals": {
                    "Type": 3.0,
                    "Integer": 0.0
                },
                "Prefix": {
                    "Type": 5.0,
                    "String": "$"
                },
                "Suffix": {
                    "Type": 5.0,
                    "String": ""
                },
                "ThousandsSep": {
                    "Type": 2.0,
                    "Boolean": 1.0
                },
                "Editable": {
                    "Type": 2.0,
                    "Boolean": 1.0
                },
                "ForeColour": {
                    "Type": 4.0,
                    "Color": {
                        "Red": 0.0,
                        "Green": 0.0,
                        "Blue": 0.0,
                        "Alpha": 255.0
                    }
                },
                "BackColour": {
                    "Type": 4.0,
                    "Color": {
                        "Red": 255.0,
                        "Green": 255.0,
                        "Blue": 255.0,
                        "Alpha": 255.0
                    }
                },
                "TabOrder": {
                    "Type": 3.0,
                    "Integer": -1.0
                }
            }
        },
        "ToolTipCtrl": {
            "Visible": 1.0,
            "ObjectProperties": {
                "Name": {
                    "Type": 5.0,
                    "String": "tt_debt_service_reserve_account_cost"
                },
                "X": {
                    "Type": 3.0,
                    "Integer": 441.0
                },
                "Y": {
                    "Type": 3.0,
                    "Integer": 102.0
                },
                "Width": {
                    "Type": 3.0,
                    "Integer": 24.0
                },
                "Height": {
                    "Type": 3.0,
                    "Integer": 24.0
                },
                "Tool Tip": {
                    "Type": 5.0,
                    "String": ""
                },
                "Tips": {
                    "Type": 5.0,
                    "String": ""
                },
                "TipTitle": {
                    "Type": 5.0,
                    "String": "Type a tip title here or define in runtime/help/tooltips.json"
                }
            }
        },
        "ToolTipCtrl": {
            "Visible": 1.0,
            "ObjectProperties": {
                "Name": {
                    "Type": 5.0,
                    "String": "tt_decommissioning_reserve_account_cost"
                },
                "X": {
                    "Type": 3.0,
                    "Integer": 441.0
                },
                "Y": {
                    "Type": 3.0,
                    "Integer": 132.0
                },
                "Width": {
                    "Type": 3.0,
                    "Integer": 24.0
                },
                "Height": {
                    "Type": 3.0,
                    "Integer": 24.0
                },
                "Tool Tip": {
                    "Type": 5.0,
                    "String": ""
                },
                "Tips": {
                    "Type": 5.0,
                    "String": ""
                },
                "TipTitle": {
                    "Type": 5.0,
                    "String": "Type a tip title here or define in runtime/help/tooltips.json"
                }
            }
        },
        "ToolTipCtrl": {
            "Visible": 1.0,
            "ObjectProperties": {
                "Name": {
                    "Type": 5.0,
                    "String": "tt_maintenance_reserve_account_cost"
                },
                "X": {
                    "Type": 3.0,
                    "Integer": 441.0
                },
                "Y": {
                    "Type": 3.0,
                    "Integer": 72.0
                },
                "Width": {
                    "Type": 3.0,
                    "Integer": 24.0
                },
                "Height": {
                    "Type": 3.0,
                    "Integer": 24.0
                },
                "Tool Tip": {
                    "Type": 5.0,
                    "String": ""
                },
                "Tips": {
                    "Type": 5.0,
                    "String": ""
                },
                "TipTitle": {
                    "Type": 5.0,
                    "String": "Type a tip title here or define in runtime/help/tooltips.json"
                }
            }
        },
        "ToolTipCtrl": {
            "Visible": 1.0,
            "ObjectProperties": {
                "Name": {
                    "Type": 5.0,
                    "String": "tt_other_reserve_accounts_cost"
                },
                "X": {
                    "Type": 3.0,
                    "Integer": 441.0
                },
                "Y": {
                    "Type": 3.0,
                    "Integer": 162.0
                },
                "Width": {
                    "Type": 3.0,
                    "Integer": 24.0
                },
                "Height": {
                    "Type": 3.0,
                    "Integer": 24.0
                },
                "Tool Tip": {
                    "Type": 5.0,
                    "String": ""
                },
                "Tips": {
                    "Type": 5.0,
                    "String": ""
                },
                "TipTitle": {
                    "Type": 5.0,
                    "String": "Type a tip title here or define in runtime/help/tooltips.json"
                }
            }
        }
    },
    "VarDatabase": {
        "financial_override_check": {
            "Version": 4.0,
            "Type": 1.0,
            "Label": " ",
            "Units": " ",
            "Group": "ME Costs - Financial",
            "IndexLabels": "",
            "Flags": 8.0,
            "DefaultValue": 0.0,
            "UIObject": "Default",
            "sscVariableName": "",
            "sscVariableValue": ""
        },
        "insurance_during_construction_cost_modeled_ui": {
            "Version": 4.0,
            "Type": 1.0,
            "Label": " ",
            "Units": " ",
            "Group": "ME Costs - Financial",
            "IndexLabels": "",
            "Flags": 8.0,
            "DefaultValue": 0.0,
            "UIObject": "Default",
            "sscVariableName": "",
            "sscVariableValue": ""
        },
        "project_contingency_cost_modeled_ui": {
            "Version": 4.0,
            "Type": 1.0,
            "Label": " ",
            "Units": " ",
            "Group": "ME Costs - Financial",
            "IndexLabels": "",
            "Flags": 8.0,
            "DefaultValue": 0.0,
            "UIObject": "Default",
            "sscVariableName": "",
            "sscVariableValue": ""
        },
        "reserve_accounts_cost_modeled_ui": {
            "Version": 4.0,
            "Type": 1.0,
            "Label": " ",
            "Units": " ",
            "Group": "ME Costs - Financial",
            "IndexLabels": "",
            "Flags": 8.0,
            "DefaultValue": 0.0,
            "UIObject": "Default",
            "sscVariableName": "",
            "sscVariableValue": ""
        }
    },
    "Equations": [
        "equations {'project_contingency_budget_cost'} = define() {",
        "\treturn ?${project_contingency_cost_method}",
        "\t\t\t[",
        "\t\t\t\t${project_contingency_cost_input}*${system_capacity},",
        "\t\t\t\t${project_contingency_cost_input},",
        "\t\t\t\t${project_contingency_cost_modeled_ui}",
        "\t\t\t];",
        "};",
        "",
        "equations {'itemized_check_contingency'} = define() {",
        "\treturn ?${project_contingency_cost_method}",
        "\t\t\t[",
        "\t\t\t\t0,",
        "\t\t\t\t0,",
        "\t\t\t\t1",
        "\t\t\t];",
        "};",
        "",
        "equations {'insurance_during_construction_cost'} = define() {",
        "\treturn ?${insurance_during_construction_method}",
        "\t\t\t[",
        "\t\t\t\t${insurance_during_construction_cost_input}*${system_capacity},",
        "\t\t\t\t${insurance_during_construction_cost_input},",
        "\t\t\t\t${insurance_during_construction_cost_modeled_ui}",
        "\t\t\t];",
        "};",
        "",
        "equations {'itemized_check_construction_insurance'} = define() {",
        "\treturn ?${insurance_during_construction_method}",
        "\t\t\t[",
        "\t\t\t\t0,",
        "\t\t\t\t0,",
        "\t\t\t\t1",
        "\t\t\t];",
        "};",
        "",
        "equations {'reserve_accounts_cost_total'} = define() {",
        "\treturn ${maintenance_reserve_account_cost}+${debt_service_reserve_account_cost}+",
        "\t\t${decommissioning_reserve_account_cost}+${other_reserve_account_cost};",
        "};",
        "",
        "equations {'reserve_accounts_cost'} = define() {",
        "\treturn ?${reserve_accounts_cost_method}",
        "\t\t\t[",
        "\t\t\t\t${reserve_accounts_cost_input}*${system_capacity},",
        "\t\t\t\t${reserve_accounts_cost_input},",
        "\t\t\t\t${reserve_accounts_cost_modeled_ui},",
        "\t\t\t\t${reserve_accounts_cost_total}",
        "\t\t\t];",
        "};",
        "",
        "equations {'itemized_check_reserve_accounts'} = define() {",
        "\tif (${financial_cost_override}!=1)",
        "\t{",
        "\t\treturn ?${reserve_accounts_cost_method}",
        "\t\t\t\t[",
        "\t\t\t\t\t0,",
        "\t\t\t\t\t0,",
        "\t\t\t\t\t2,",
        "\t\t\t\t\t1",
        "\t\t\t\t];",
        "\t}",
        "\telse",
        "\t{",
        "\t\treturn 2;",
        "\t}",
        "};",
        "",
        "equations {'itemized_check_other_financial'} = define() {",
        "\treturn ?${other_financial_cost_method}",
        "\t\t\t[",
        "\t\t\t\t0,",
        "\t\t\t\t0,",
        "\t\t\t\t1",
        "\t\t\t];",
        "};",
        "",
        "equations {'other_financial_cost_modeled'} = define() {",
        "\treturn 0;",
        "};",
        "",
        "equations {'other_financial_cost'} = define() {",
        "\treturn ?${other_financial_cost_method}",
        "\t\t\t[",
        "\t\t\t\t${other_financial_cost_input}*${system_capacity},",
        "\t\t\t\t${other_financial_cost_input},",
        "\t\t\t\t${other_financial_cost_modeled}",
        "\t\t\t];",
        "};",
        "",
        "equations {'financial_override_check'} = define() {",
        "\treturn ${financial_cost_override};};",
        "",
        "",
        ""
    ],
    "Callbacks": [
        "on_load{'Marine Costs - Financial Itemized'} = define() {",
        "\ton_change{'itemized_check_contingency'};",
        "\tenable_contingency();",
        "\ton_change{'itemized_check_construction_insurance'};",
        "\tenable_construction_insurance();",
        "\ton_change{'itemized_check_reserve_accounts'};",
        "\tenable_reserve_accounts();",
        "\ton_change{'itemized_check_other_financial'};",
        "\tenable_other_financial();",
        "\ton_change{'financial_override_check'};",
        "\tcheck_override_financial();",
        "};",
        "",
        "on_change{'financial_override_check'} = define() {",
        "\tcheck_override_financial();",
        "};",
        "",
        "function check_override_financial()",
        "{\t",
        "\tcheck_value = value('financial_override_check');",
        "\t//enable('project_contingency_cost_method',check_value!=1);",
        "\t//enable('project_contingency_budget_cost',check_value!=1);",
        "\t//enable('insurance_during_construction_method',check_value!=1);",
        "\t//enable('insurance_during_construction_cost',check_value!=1);",
        "\t//enable('reserve_accounts_cost_method',check_value!=1);",
        "\t//enable('reserve_accounts_cost',check_value!=1);",
        "\t//enable('other_financial_cost_method',check_value!=1);",
        "\t//enable('other_financial_cost',check_value!=1);",
        "\tshow('financial_override_label',check_value==1);",
        "\trefresh();",
        "}",
        "",
        "on_change{'itemized_check_contingency'} = define() {",
        "\tenable_contingency();",
        "};",
        "",
        "function enable_contingency() ",
        "{",
        "\titemized_value = value('itemized_check_contingency');",
        "\tenable('project_contingency_cost_input',itemized_value!=1);",
        "\toverride_financial_cost();",
        "\trefresh();",
        "}",
        "",
        "on_change{'itemized_check_construction_insurance'} = define() {",
        "\tenable_construction_insurance();",
        "};",
        "",
        "function enable_construction_insurance()",
        "{",
        "\titemized_value_const = value('itemized_check_construction_insurance');",
        "\tenable('insurance_during_construction_cost_input',itemized_value_const!=1);",
        "\toverride_financial_cost();",
        "\trefresh();",
        "}",
        "",
        "on_change{'itemized_check_reserve_accounts'} = define() {",
        "\tenable_reserve_accounts();",
        "};",
        "",
        "function enable_reserve_accounts()",
        "{",
        "\titemized_value_reserve = value('itemized_check_reserve_accounts');",
        "\tenable('maintenance_reserve_account_cost',itemized_value_reserve==1);",
        "\tenable('detailed_cost_choice_reserve_accounts',itemized_value_reserve==1);",
        "\tenable('debt_service_reserve_account_cost',itemized_value_reserve==1);",
        "\tenable('decommissioning_reserve_account_cost',itemized_value_reserve==1);",
        "\tenable('other_reserve_account_cost',itemized_value_reserve==1);",
        "\tenable('reserve_accounts_cost_input',itemized_value_reserve!=2);",
        "\tshow('reserve_accounts_cost_total',itemized_value_reserve==1);",
        "\tshow('reserve_total_label',itemized_value_reserve==1);",
        "\tshow('reserve_accounts_cost_input',(itemized_value_reserve==0 || itemized_value_reserve==2));",
        "\tshow('reserve_input_label',(itemized_value_reserve==0 || itemized_value_reserve==2));",
        "\t",
        "\toverride_financial_cost();",
        "\trefresh();",
        "}",
        "",
        "on_change{'itemized_check_other_financial'} = define() {",
        "\tenable_other_financial();",
        "};",
        "",
        "function enable_other_financial() ",
        "{",
        "\titemized_value_other = value('itemized_check_other_financial');",
        "\tenable('other_financial_cost_input',itemized_value_other!=1);",
        "\toverride_financial_cost();",
        "\trefresh();",
        "}",
        "",
        "",
        ""
    ]
}